jschema_to_python/__init__.py
jschema_to_python/__main__.py
jschema_to_python/class_generator.py
jschema_to_python/driver.py
jschema_to_python/init_file_generator.py
jschema_to_python/object_model_module_generator.py
jschema_to_python/python_file_generator.py
jschema_to_python/to_json.py
jschema_to_python/utilities.py
jschema_to_python-1.2.3.dist-info/AUTHORS
jschema_to_python-1.2.3.dist-info/LICENSE
jschema_to_python-1.2.3.dist-info/METADATA
jschema_to_python-1.2.3.dist-info/WHEEL
jschema_to_python-1.2.3.dist-info/pbr.json
jschema_to_python-1.2.3.dist-info/top_level.txt
jschema_to_python-1.2.3.dist-info/RECORD
