Metadata-Version: 1.2
Name: jschema_to_python
Version: 1.2.3
Summary: Generate source code for Python classes from a JSON schema.
Home-page: https://github.com/microsoft/jschema-to-python
Author: Microsoft Corporation
Author-email: v-lgold@microsoft.com
License: MIT
Platform: UNKNOWN
Classifier: Development Status :: 5 - Production/Stable
Classifier: Environment :: Console
Classifier: Intended Audience :: Developers
Classifier: Intended Audience :: Information Technology
Classifier: License :: OSI Approved :: MIT License
Classifier: Operating System :: OS Independent
Classifier: Programming Language :: Python
Classifier: Topic :: Software Development :: Libraries :: Python Modules
Requires-Python: >= 2.7
